ltfi_wsap/__init__.py
ltfi_wsap/client.py
ltfi_wsap/exceptions.py
ltfi_wsap/models.py
ltfi_wsap_sdk-2.0.3.dist-info/licenses/LICENSE
ltfi_wsap_sdk-2.0.3.dist-info/licenses/NOTICE
ltfi_wsap_sdk-2.0.3.dist-info/METADATA
ltfi_wsap_sdk-2.0.3.dist-info/WHEEL
ltfi_wsap_sdk-2.0.3.dist-info/entry_points.txt
ltfi_wsap_sdk-2.0.3.dist-info/top_level.txt
ltfi_wsap_sdk-2.0.3.dist-info/RECORD
